CHANGES.txt
LICENSE.txt
MANIFEST.in
README.md
setup.py
django_youtube/__init__.py
django_youtube/admin.py
django_youtube/api.py
django_youtube/forms.py
django_youtube/models.py
django_youtube/tests.py
django_youtube/urls.py
django_youtube/views.py
django_youtube.egg-info/PKG-INFO
django_youtube.egg-info/SOURCES.txt
django_youtube.egg-info/dependency_links.txt
django_youtube.egg-info/not-zip-safe
django_youtube.egg-info/top_level.txt
django_youtube/tastypie/__init__.py
django_youtube/tastypie/resources.py
django_youtube/templates/django_youtube/direct-upload.html
django_youtube/templates/django_youtube/upload.html
django_youtube/templates/django_youtube/video.html
django_youtube/templates/django_youtube/video_failed.html
django_youtube/templates/django_youtube/video_unavailable.html
django_youtube/templates/django_youtube/videos.html