Metadata-Version: 1.0
Name: django-youtube
Version: 0.2
Summary: Youtube API wrapper app for Django. It helps to upload, display, delete, update videos from Youtube
Home-page: https://github.com/laplacesdemon/django-youtube
Author: Suleyman Melikoglu
Author-email: suleyman@melikoglu.info
License: BSD licence, see LICENCE.txt
Platform: UNKNOWN
